heptagon/__init__.py
heptagon-0.0.1.dist-info/LICENSE.md
heptagon-0.0.1.dist-info/METADATA
heptagon-0.0.1.dist-info/WHEEL
heptagon-0.0.1.dist-info/entry_points.txt
heptagon-0.0.1.dist-info/top_level.txt
heptagon-0.0.1.dist-info/RECORD
