Metadata-Version: 2.1
Name: heptagon
Version: 0.0.1
Summary: heptagon to build python flavored hexagonal applications
Author-email: Juan Cerezo <juancerezo.pro@gmail.com>
License: MIT License
Classifier: Programming Language :: Python :: 3
Requires-Python: >=3.10
License-File: LICENSE.md
Requires-Dist: pydantic >=2.5
